<?xml version="1.0" encoding="UTF-8"?>
<mets xmlns="http://www.loc.gov/METS/" xmlns:xsi="http://www.w3.org/2001/XMLSchema-instance"
   xmlns:mix="http://www.loc.gov/mix/" xmlns:xlink="http://www.w3.org/1999/xlink"
   xmlns:local="http://diglib.princeton.edu" xmlns:mods="http://www.loc.gov/mods/v3"
   xsi:schemaLocation="http://www.loc.gov/METS/ http://www.loc.gov/standards/mets/mets.xsd http://www.loc.gov/mix/ http://schema.ccs-gmbh.com/docworks/version20/mix_jp2.xsd http://www.loc.gov/mods/v3 http://www.loc.gov/standards/mods/v3/mods-3-5.xsd"
   TYPE="Magazine" OBJID="urn:PUL:periodicals:bluemountain:bmtnaao_1915-07_01">
   <metsHdr>
      <agent ROLE="CREATOR" TYPE="ORGANIZATION">
         <name>Princeton University Library, Digital Initiatives</name>
         <note>docWORKS-ID: 900</note>
      </agent>
      <metsDocumentID TYPE="URN">urn:PUL:bluemountain:td:bmtnaao_1915-07_01</metsDocumentID>
   </metsHdr>
   <dmdSec ID="dmd1">
      <mdWrap MDTYPE="MODS">
         <xmlData>
            <mods xmlns="http://www.loc.gov/mods/v3">
               <recordInfo>
                  <recordIdentifier>urn:PUL:bluemountain:dmd:bmtnaao_1915-07_01</recordIdentifier>
               </recordInfo>
               <identifier type="bmtn">urn:PUL:bluemountain:bmtnaao_1915-07_01</identifier>
               <typeOfResource>text</typeOfResource>
               <genre>Periodicals-Issue</genre>
               <titleInfo>
                  <title>291</title>
               </titleInfo>
               <part type="issue">
                  <detail type="number">
                     <number>5</number>
                     <number>6</number>
                     <caption>Nos. 5-6</caption>
                  </detail>
               </part>
               <originInfo>
                  <dateIssued>July-August 1915</dateIssued>
                  <dateIssued keyDate="yes" encoding="w3cdtf">1915-07</dateIssued>
                  <dateIssued encoding="w3cdtf">1915-08</dateIssued>
               </originInfo>
               <location>
                  <physicalLocation type="text">Princeton University. Department of Rare Books and Special Collections</physicalLocation>
                  <physicalLocation authority="marcorg" type="code">NjP</physicalLocation>
                  <holdingSimple>
                     <copyInformation>
                        <subLocation>Oversize GAX 2007-0018E</subLocation>
                     </copyInformation>
                  </holdingSimple>
               </location>
               <relatedItem type="host" xlink:type="simple"
                  xlink:href="urn:PUL:bluemountain:bmtnaao">
                  <recordInfo>
                     <recordIdentifier>urn:PUL:bluemountain:dmd:bmtnaao</recordIdentifier>
                  </recordInfo>
               </relatedItem>
               <relatedItem type="constituent" ID="c001">
                  <titleInfo lang="eng">
                     <title>ICI, C’EST ICI STIEGLITZ FOI ET AMOUR</title>
                  </titleInfo>
                  <name type="personal" authority="viaf" valueURI="http://viaf.org/viaf/36923084">
	                    <displayForm>F. Picabia</displayForm>
	                    <role>
		                      <roleTerm type="code" authority="marcrelator">cre</roleTerm>
	                    </role>
	                 </name>
                  <note type="caption">1915 New York</note>
                  <typeOfResource>still image</typeOfResource>
                  <part>
                     <extent unit="page">
                        <start>1</start>
                     </extent>
                  </part>
                  <genre type="CCS">Illustration</genre>
               </relatedItem>
               <relatedItem type="constituent" ID="c002">
                  <titleInfo lang="eng">
                     <nonSort>LE</nonSort>
                     <title>SAINT DES SAINTS C’EST DE MOI QU’IL S’AGIT DANS CE PORTRAIT</title>
                  </titleInfo>
                  <name type="personal" authority="viaf" valueURI="http://viaf.org/viaf/36923084">
	                    <displayForm>F. Picabia</displayForm>
	                    <role>
		                      <roleTerm type="code" authority="marcrelator">cre</roleTerm>
	                    </role>
	                 </name>
                  <note type="caption">Juillet 1915 New York</note>
                  <typeOfResource>still image</typeOfResource>
                  <part>
                     <extent unit="page">
                        <start>2</start>
                     </extent>
                  </part>
                  <genre type="CCS">Illustration</genre>
               </relatedItem>
               <relatedItem type="constituent" ID="c003">
                  <titleInfo lang="eng">
                     <title>VOILA HAVILAND</title>
                     <subTitle>LA POESIE EST COMME LUI</subTitle>
                  </titleInfo>
                  <note type="caption">1915 New York</note>
                  <name type="personal" authority="viaf" valueURI="http://viaf.org/viaf/36923084">
	                    <displayForm>F. Picabia</displayForm>
	                    <role>
		                      <roleTerm type="code" authority="marcrelator">cre</roleTerm>
	                    </role>
	                 </name>
                  <typeOfResource>still image</typeOfResource>
                  <part>
                     <extent unit="page">
                        <start>3</start>
                     </extent>
                  </part>
                  <genre type="CCS">Illustration</genre>
               </relatedItem>
               <relatedItem type="constituent" ID="c004">
                  <titleInfo lang="eng">
                     <title>PORTRAIT D’UNE JEUNE FILLE AMERICAINE DANS L’ETAT DE NUDITÉ</title>
                  </titleInfo>
                  <name type="personal" authority="viaf" valueURI="http://viaf.org/viaf/36923084">
	                    <displayForm>F Picabia</displayForm>
	                    <role>
		                      <roleTerm type="code" authority="marcrelator">cre</roleTerm>
	                    </role>
	                 </name>
                  <note type="caption">5 Juillet 1915 New York</note>
                  <typeOfResource>still image</typeOfResource>
                  <part>
                     <extent unit="page">
                        <start>4</start>
                     </extent>
                  </part>
                  <genre type="CCS">Illustration</genre>
               </relatedItem>
               <relatedItem type="constituent" ID="c005">
                  <titleInfo lang="eng">
                     <title>DE ZAYAS! DE ZAYAS!</title>
                  </titleInfo>
                  <name type="personal" authority="viaf" valueURI="http://viaf.org/viaf/36923084">
	                    <displayForm>F. Picabia</displayForm>
	                    <role>
		                      <roleTerm type="code" authority="marcrelator">cre</roleTerm>
	                    </role>
	                 </name>
                  <note type="caption">1915 New York</note>
                  <typeOfResource>still image</typeOfResource>
                  <part>
                     <extent unit="page">
                        <start>5</start>
                     </extent>
                  </part>
                  <genre type="CCS">Illustration</genre>
               </relatedItem>
               <relatedItem type="constituent" ID="c006">
                  <titleInfo lang="eng">
                     <title>Untitled text</title>
                  </titleInfo>
                  <name type="personal" authority="viaf" valueURI="http://viaf.org/viaf/5080960">
	                    <displayForm>M. De Zayas</displayForm>
	                    <role>
		                      <roleTerm type="code" authority="marcrelator">cre</roleTerm>
	                    </role>
	                 </name>
                  <typeOfResource>text</typeOfResource>
                  <language>
                     <languageTerm authority="iso639-2b">eng</languageTerm>
                  </language>
                  <part>
                     <extent unit="page">
                        <start>6</start>
                     </extent>
                  </part>
                  <genre type="CCS">TextContent</genre>
               </relatedItem>
               <relatedItem type="constituent" ID="c007">
                  <titleInfo lang="eng">
                     <title>Untitled text</title>
                  </titleInfo>
                  <name type="personal" authority="viaf" valueURI="http://viaf.org/viaf/5080960">
	                    <displayForm>M. De Zayas</displayForm>
	                    <role>
		                      <roleTerm type="code" authority="marcrelator">cre</roleTerm>
	                    </role>
	                 </name>
                  <typeOfResource>text</typeOfResource>
                  <language>
                     <languageTerm authority="iso639-2b">eng</languageTerm>
                  </language>
                  <part>
                     <extent unit="page">
                        <start>6</start>
                     </extent>
                  </part>
                  <genre type="CCS">TextContent</genre>
               </relatedItem>
            </mods>
         </xmlData>
      </mdWrap>
   </dmdSec>
   <amdSec>
      <techMD ID="techmd1">
         <mdWrap MDTYPE="NISOIMG">
            <xmlData>
               <mix:mix>
                  <mix:BasicImageParameters>
                     <mix:Format>
                        <mix:MIMEType>image/jp2</mix:MIMEType>
                        <mix:ByteOrder>little-endian</mix:ByteOrder>
                        <mix:Compression>
                           <mix:CompressionScheme>34712</mix:CompressionScheme>
                        </mix:Compression>
                        <mix:PhotometricInterpretation>
                           <mix:ColorSpace>2</mix:ColorSpace>
                        </mix:PhotometricInterpretation>
                     </mix:Format>
                     <mix:File>
                        <mix:ImageIdentifier imageIdentifierLocation="//lib-docworks1/OUT/PUL-BlueMountain/291/bmtnaao/issues/1915/07_01/alto">bmtnaao_1915-07_01_0001.jp2</mix:ImageIdentifier>
                        <mix:FileSize>1072928</mix:FileSize>
                        <mix:Orientation>1</mix:Orientation>
                        <mix:DisplayOrientation>1</mix:DisplayOrientation>
                     </mix:File>
                  </mix:BasicImageParameters>
                  <mix:ImageCreation>
                     <mix:SourceType>METAe_Serial</mix:SourceType>
                     <mix:SourceID/>
                     <mix:ImageProducer/>
                     <mix:Host>
                        <mix:HostComputer>LIB-DOCWORKS1</mix:HostComputer>
                        <mix:OperatingSystem>windows</mix:OperatingSystem>
                        <mix:OSVersion>6.1 Service Pack 1</mix:OSVersion>
                     </mix:Host>
                     <mix:DeviceSource/>
                     <mix:ScanningSystemCapture>
                        <mix:ScanningSystemHardware>
                           <mix:ScannerManufacturer/>
                           <mix:ScannerModel>
                              <mix:ScannerModelName/>
                              <mix:ScannerModelNumber/>
                              <mix:ScannerModelSerialNo/>
                           </mix:ScannerModel>
                        </mix:ScanningSystemHardware>
                        <mix:ScanningSystemSoftware>
                           <mix:ScanningSoftware>CCS docWorks</mix:ScanningSoftware>
                           <mix:ScanningSoftwareVersionNo/>
                        </mix:ScanningSystemSoftware>
                        <mix:ScannerCaptureSettings>
                           <mix:PixelSize>0.0635000</mix:PixelSize>
                           <mix:PhysScanResolution>
                              <mix:XphysScanResolution>400</mix:XphysScanResolution>
                              <mix:YphysScanResolution>400</mix:YphysScanResolution>
                           </mix:PhysScanResolution>
                        </mix:ScannerCaptureSettings>
                     </mix:ScanningSystemCapture>
                  </mix:ImageCreation>
                  <mix:ImagingPerformanceAssessment>
                     <mix:SpatialMetrics>
                        <mix:ImageWidth>2384</mix:ImageWidth>
                        <mix:ImageLength>3600</mix:ImageLength>
                     </mix:SpatialMetrics>
                     <mix:Energetics>
                        <mix:BitsPerSample>8,8,8</mix:BitsPerSample>
                        <mix:SamplesPerPixel>3</mix:SamplesPerPixel>
                     </mix:Energetics>
                  </mix:ImagingPerformanceAssessment>
                  <mix:ChangeHistory>
                     <mix:ImageProcessing>
                        <mix:SourceData>./PUL-BlueMountain/periodicals/bmtnaao/issues/1915/07_01/00000001.jp2</mix:SourceData>
                     </mix:ImageProcessing>
                  </mix:ChangeHistory>
               </mix:mix>
            </xmlData>
         </mdWrap>
      </techMD>
      <techMD ID="techmd2">
         <mdWrap MDTYPE="NISOIMG">
            <xmlData>
               <mix:mix>
                  <mix:BasicImageParameters>
                     <mix:Format>
                        <mix:MIMEType>image/jp2</mix:MIMEType>
                        <mix:ByteOrder>little-endian</mix:ByteOrder>
                        <mix:Compression>
                           <mix:CompressionScheme>34712</mix:CompressionScheme>
                        </mix:Compression>
                        <mix:PhotometricInterpretation>
                           <mix:ColorSpace>2</mix:ColorSpace>
                        </mix:PhotometricInterpretation>
                     </mix:Format>
                     <mix:File>
                        <mix:ImageIdentifier imageIdentifierLocation="//lib-docworks1/OUT/PUL-BlueMountain/291/bmtnaao/issues/1915/07_01/alto">bmtnaao_1915-07_01_0002.jp2</mix:ImageIdentifier>
                        <mix:FileSize>1068873</mix:FileSize>
                        <mix:Orientation>1</mix:Orientation>
                        <mix:DisplayOrientation>1</mix:DisplayOrientation>
                     </mix:File>
                  </mix:BasicImageParameters>
                  <mix:ImageCreation>
                     <mix:SourceType>METAe_Serial</mix:SourceType>
                     <mix:SourceID/>
                     <mix:ImageProducer/>
                     <mix:Host>
                        <mix:HostComputer>LIB-DOCWORKS1</mix:HostComputer>
                        <mix:OperatingSystem>windows</mix:OperatingSystem>
                        <mix:OSVersion>6.1 Service Pack 1</mix:OSVersion>
                     </mix:Host>
                     <mix:DeviceSource/>
                     <mix:ScanningSystemCapture>
                        <mix:ScanningSystemHardware>
                           <mix:ScannerManufacturer/>
                           <mix:ScannerModel>
                              <mix:ScannerModelName/>
                              <mix:ScannerModelNumber/>
                              <mix:ScannerModelSerialNo/>
                           </mix:ScannerModel>
                        </mix:ScanningSystemHardware>
                        <mix:ScanningSystemSoftware>
                           <mix:ScanningSoftware>CCS docWorks</mix:ScanningSoftware>
                           <mix:ScanningSoftwareVersionNo/>
                        </mix:ScanningSystemSoftware>
                        <mix:ScannerCaptureSettings>
                           <mix:PixelSize>0.0635000</mix:PixelSize>
                           <mix:PhysScanResolution>
                              <mix:XphysScanResolution>400</mix:XphysScanResolution>
                              <mix:YphysScanResolution>400</mix:YphysScanResolution>
                           </mix:PhysScanResolution>
                        </mix:ScannerCaptureSettings>
                     </mix:ScanningSystemCapture>
                  </mix:ImageCreation>
                  <mix:ImagingPerformanceAssessment>
                     <mix:SpatialMetrics>
                        <mix:ImageWidth>2375</mix:ImageWidth>
                        <mix:ImageLength>3600</mix:ImageLength>
                     </mix:SpatialMetrics>
                     <mix:Energetics>
                        <mix:BitsPerSample>8,8,8</mix:BitsPerSample>
                        <mix:SamplesPerPixel>3</mix:SamplesPerPixel>
                     </mix:Energetics>
                  </mix:ImagingPerformanceAssessment>
                  <mix:ChangeHistory>
                     <mix:ImageProcessing>
                        <mix:SourceData>./PUL-BlueMountain/periodicals/bmtnaao/issues/1915/07_01/00000002.jp2</mix:SourceData>
                     </mix:ImageProcessing>
                  </mix:ChangeHistory>
               </mix:mix>
            </xmlData>
         </mdWrap>
      </techMD>
      <techMD ID="techmd3">
         <mdWrap MDTYPE="NISOIMG">
            <xmlData>
               <mix:mix>
                  <mix:BasicImageParameters>
                     <mix:Format>
                        <mix:MIMEType>image/jp2</mix:MIMEType>
                        <mix:ByteOrder>little-endian</mix:ByteOrder>
                        <mix:Compression>
                           <mix:CompressionScheme>34712</mix:CompressionScheme>
                        </mix:Compression>
                        <mix:PhotometricInterpretation>
                           <mix:ColorSpace>2</mix:ColorSpace>
                        </mix:PhotometricInterpretation>
                     </mix:Format>
                     <mix:File>
                        <mix:ImageIdentifier imageIdentifierLocation="//lib-docworks1/OUT/PUL-BlueMountain/291/bmtnaao/issues/1915/07_01/alto">bmtnaao_1915-07_01_0003.jp2</mix:ImageIdentifier>
                        <mix:FileSize>1059395</mix:FileSize>
                        <mix:Orientation>1</mix:Orientation>
                        <mix:DisplayOrientation>1</mix:DisplayOrientation>
                     </mix:File>
                  </mix:BasicImageParameters>
                  <mix:ImageCreation>
                     <mix:SourceType>METAe_Serial</mix:SourceType>
                     <mix:SourceID/>
                     <mix:ImageProducer/>
                     <mix:Host>
                        <mix:HostComputer>LIB-DOCWORKS1</mix:HostComputer>
                        <mix:OperatingSystem>windows</mix:OperatingSystem>
                        <mix:OSVersion>6.1 Service Pack 1</mix:OSVersion>
                     </mix:Host>
                     <mix:DeviceSource/>
                     <mix:ScanningSystemCapture>
                        <mix:ScanningSystemHardware>
                           <mix:ScannerManufacturer/>
                           <mix:ScannerModel>
                              <mix:ScannerModelName/>
                              <mix:ScannerModelNumber/>
                              <mix:ScannerModelSerialNo/>
                           </mix:ScannerModel>
                        </mix:ScanningSystemHardware>
                        <mix:ScanningSystemSoftware>
                           <mix:ScanningSoftware>CCS docWorks</mix:ScanningSoftware>
                           <mix:ScanningSoftwareVersionNo/>
                        </mix:ScanningSystemSoftware>
                        <mix:ScannerCaptureSettings>
                           <mix:PixelSize>0.0635000</mix:PixelSize>
                           <mix:PhysScanResolution>
                              <mix:XphysScanResolution>400</mix:XphysScanResolution>
                              <mix:YphysScanResolution>400</mix:YphysScanResolution>
                           </mix:PhysScanResolution>
                        </mix:ScannerCaptureSettings>
                     </mix:ScanningSystemCapture>
                  </mix:ImageCreation>
                  <mix:ImagingPerformanceAssessment>
                     <mix:SpatialMetrics>
                        <mix:ImageWidth>2354</mix:ImageWidth>
                        <mix:ImageLength>3600</mix:ImageLength>
                     </mix:SpatialMetrics>
                     <mix:Energetics>
                        <mix:BitsPerSample>8,8,8</mix:BitsPerSample>
                        <mix:SamplesPerPixel>3</mix:SamplesPerPixel>
                     </mix:Energetics>
                  </mix:ImagingPerformanceAssessment>
                  <mix:ChangeHistory>
                     <mix:ImageProcessing>
                        <mix:SourceData>./PUL-BlueMountain/periodicals/bmtnaao/issues/1915/07_01/00000003.jp2</mix:SourceData>
                     </mix:ImageProcessing>
                  </mix:ChangeHistory>
               </mix:mix>
            </xmlData>
         </mdWrap>
      </techMD>
      <techMD ID="techmd4">
         <mdWrap MDTYPE="NISOIMG">
            <xmlData>
               <mix:mix>
                  <mix:BasicImageParameters>
                     <mix:Format>
                        <mix:MIMEType>image/jp2</mix:MIMEType>
                        <mix:ByteOrder>little-endian</mix:ByteOrder>
                        <mix:Compression>
                           <mix:CompressionScheme>34712</mix:CompressionScheme>
                        </mix:Compression>
                        <mix:PhotometricInterpretation>
                           <mix:ColorSpace>2</mix:ColorSpace>
                        </mix:PhotometricInterpretation>
                     </mix:Format>
                     <mix:File>
                        <mix:ImageIdentifier imageIdentifierLocation="//lib-docworks1/OUT/PUL-BlueMountain/291/bmtnaao/issues/1915/07_01/alto">bmtnaao_1915-07_01_0004.jp2</mix:ImageIdentifier>
                        <mix:FileSize>1059294</mix:FileSize>
                        <mix:Orientation>1</mix:Orientation>
                        <mix:DisplayOrientation>1</mix:DisplayOrientation>
                     </mix:File>
                  </mix:BasicImageParameters>
                  <mix:ImageCreation>
                     <mix:SourceType>METAe_Serial</mix:SourceType>
                     <mix:SourceID/>
                     <mix:ImageProducer/>
                     <mix:Host>
                        <mix:HostComputer>LIB-DOCWORKS1</mix:HostComputer>
                        <mix:OperatingSystem>windows</mix:OperatingSystem>
                        <mix:OSVersion>6.1 Service Pack 1</mix:OSVersion>
                     </mix:Host>
                     <mix:DeviceSource/>
                     <mix:ScanningSystemCapture>
                        <mix:ScanningSystemHardware>
                           <mix:ScannerManufacturer/>
                           <mix:ScannerModel>
                              <mix:ScannerModelName/>
                              <mix:ScannerModelNumber/>
                              <mix:ScannerModelSerialNo/>
                           </mix:ScannerModel>
                        </mix:ScanningSystemHardware>
                        <mix:ScanningSystemSoftware>
                           <mix:ScanningSoftware>CCS docWorks</mix:ScanningSoftware>
                           <mix:ScanningSoftwareVersionNo/>
                        </mix:ScanningSystemSoftware>
                        <mix:ScannerCaptureSettings>
                           <mix:PixelSize>0.0635000</mix:PixelSize>
                           <mix:PhysScanResolution>
                              <mix:XphysScanResolution>400</mix:XphysScanResolution>
                              <mix:YphysScanResolution>400</mix:YphysScanResolution>
                           </mix:PhysScanResolution>
                        </mix:ScannerCaptureSettings>
                     </mix:ScanningSystemCapture>
                  </mix:ImageCreation>
                  <mix:ImagingPerformanceAssessment>
                     <mix:SpatialMetrics>
                        <mix:ImageWidth>2354</mix:ImageWidth>
                        <mix:ImageLength>3600</mix:ImageLength>
                     </mix:SpatialMetrics>
                     <mix:Energetics>
                        <mix:BitsPerSample>8,8,8</mix:BitsPerSample>
                        <mix:SamplesPerPixel>3</mix:SamplesPerPixel>
                     </mix:Energetics>
                  </mix:ImagingPerformanceAssessment>
                  <mix:ChangeHistory>
                     <mix:ImageProcessing>
                        <mix:SourceData>./PUL-BlueMountain/periodicals/bmtnaao/issues/1915/07_01/00000005.jp2</mix:SourceData>
                     </mix:ImageProcessing>
                  </mix:ChangeHistory>
               </mix:mix>
            </xmlData>
         </mdWrap>
      </techMD>
      <techMD ID="techmd5">
         <mdWrap MDTYPE="NISOIMG">
            <xmlData>
               <mix:mix>
                  <mix:BasicImageParameters>
                     <mix:Format>
                        <mix:MIMEType>image/jp2</mix:MIMEType>
                        <mix:ByteOrder>little-endian</mix:ByteOrder>
                        <mix:Compression>
                           <mix:CompressionScheme>34712</mix:CompressionScheme>
                        </mix:Compression>
                        <mix:PhotometricInterpretation>
                           <mix:ColorSpace>2</mix:ColorSpace>
                        </mix:PhotometricInterpretation>
                     </mix:Format>
                     <mix:File>
                        <mix:ImageIdentifier imageIdentifierLocation="//lib-docworks1/OUT/PUL-BlueMountain/291/bmtnaao/issues/1915/07_01/alto">bmtnaao_1915-07_01_0005.jp2</mix:ImageIdentifier>
                        <mix:FileSize>1059407</mix:FileSize>
                        <mix:Orientation>1</mix:Orientation>
                        <mix:DisplayOrientation>1</mix:DisplayOrientation>
                     </mix:File>
                  </mix:BasicImageParameters>
                  <mix:ImageCreation>
                     <mix:SourceType>METAe_Serial</mix:SourceType>
                     <mix:SourceID/>
                     <mix:ImageProducer/>
                     <mix:Host>
                        <mix:HostComputer>LIB-DOCWORKS1</mix:HostComputer>
                        <mix:OperatingSystem>windows</mix:OperatingSystem>
                        <mix:OSVersion>6.1 Service Pack 1</mix:OSVersion>
                     </mix:Host>
                     <mix:DeviceSource/>
                     <mix:ScanningSystemCapture>
                        <mix:ScanningSystemHardware>
                           <mix:ScannerManufacturer/>
                           <mix:ScannerModel>
                              <mix:ScannerModelName/>
                              <mix:ScannerModelNumber/>
                              <mix:ScannerModelSerialNo/>
                           </mix:ScannerModel>
                        </mix:ScanningSystemHardware>
                        <mix:ScanningSystemSoftware>
                           <mix:ScanningSoftware>CCS docWorks</mix:ScanningSoftware>
                           <mix:ScanningSoftwareVersionNo/>
                        </mix:ScanningSystemSoftware>
                        <mix:ScannerCaptureSettings>
                           <mix:PixelSize>0.0635000</mix:PixelSize>
                           <mix:PhysScanResolution>
                              <mix:XphysScanResolution>400</mix:XphysScanResolution>
                              <mix:YphysScanResolution>400</mix:YphysScanResolution>
                           </mix:PhysScanResolution>
                        </mix:ScannerCaptureSettings>
                     </mix:ScanningSystemCapture>
                  </mix:ImageCreation>
                  <mix:ImagingPerformanceAssessment>
                     <mix:SpatialMetrics>
                        <mix:ImageWidth>2354</mix:ImageWidth>
                        <mix:ImageLength>3600</mix:ImageLength>
                     </mix:SpatialMetrics>
                     <mix:Energetics>
                        <mix:BitsPerSample>8,8,8</mix:BitsPerSample>
                        <mix:SamplesPerPixel>3</mix:SamplesPerPixel>
                     </mix:Energetics>
                  </mix:ImagingPerformanceAssessment>
                  <mix:ChangeHistory>
                     <mix:ImageProcessing>
                        <mix:SourceData>./PUL-BlueMountain/periodicals/bmtnaao/issues/1915/07_01/00000006.jp2</mix:SourceData>
                     </mix:ImageProcessing>
                  </mix:ChangeHistory>
               </mix:mix>
            </xmlData>
         </mdWrap>
      </techMD>
      <techMD ID="techmd6">
         <mdWrap MDTYPE="NISOIMG">
            <xmlData>
               <mix:mix>
                  <mix:BasicImageParameters>
                     <mix:Format>
                        <mix:MIMEType>image/jp2</mix:MIMEType>
                        <mix:ByteOrder>little-endian</mix:ByteOrder>
                        <mix:Compression>
                           <mix:CompressionScheme>34712</mix:CompressionScheme>
                        </mix:Compression>
                        <mix:PhotometricInterpretation>
                           <mix:ColorSpace>2</mix:ColorSpace>
                        </mix:PhotometricInterpretation>
                     </mix:Format>
                     <mix:File>
                        <mix:ImageIdentifier imageIdentifierLocation="//lib-docworks1/OUT/PUL-BlueMountain/291/bmtnaao/issues/1915/07_01/alto">bmtnaao_1915-07_01_0006.jp2</mix:ImageIdentifier>
                        <mix:FileSize>1071093</mix:FileSize>
                        <mix:Orientation>1</mix:Orientation>
                        <mix:DisplayOrientation>1</mix:DisplayOrientation>
                     </mix:File>
                  </mix:BasicImageParameters>
                  <mix:ImageCreation>
                     <mix:SourceType>METAe_Serial</mix:SourceType>
                     <mix:SourceID/>
                     <mix:ImageProducer/>
                     <mix:Host>
                        <mix:HostComputer>LIB-DOCWORKS1</mix:HostComputer>
                        <mix:OperatingSystem>windows</mix:OperatingSystem>
                        <mix:OSVersion>6.1 Service Pack 1</mix:OSVersion>
                     </mix:Host>
                     <mix:DeviceSource/>
                     <mix:ScanningSystemCapture>
                        <mix:ScanningSystemHardware>
                           <mix:ScannerManufacturer/>
                           <mix:ScannerModel>
                              <mix:ScannerModelName/>
                              <mix:ScannerModelNumber/>
                              <mix:ScannerModelSerialNo/>
                           </mix:ScannerModel>
                        </mix:ScanningSystemHardware>
                        <mix:ScanningSystemSoftware>
                           <mix:ScanningSoftware>CCS docWorks</mix:ScanningSoftware>
                           <mix:ScanningSoftwareVersionNo/>
                        </mix:ScanningSystemSoftware>
                        <mix:ScannerCaptureSettings>
                           <mix:PixelSize>0.0635000</mix:PixelSize>
                           <mix:PhysScanResolution>
                              <mix:XphysScanResolution>400</mix:XphysScanResolution>
                              <mix:YphysScanResolution>400</mix:YphysScanResolution>
                           </mix:PhysScanResolution>
                        </mix:ScannerCaptureSettings>
                     </mix:ScanningSystemCapture>
                  </mix:ImageCreation>
                  <mix:ImagingPerformanceAssessment>
                     <mix:SpatialMetrics>
                        <mix:ImageWidth>2380</mix:ImageWidth>
                        <mix:ImageLength>3600</mix:ImageLength>
                     </mix:SpatialMetrics>
                     <mix:Energetics>
                        <mix:BitsPerSample>8,8,8</mix:BitsPerSample>
                        <mix:SamplesPerPixel>3</mix:SamplesPerPixel>
                     </mix:Energetics>
                  </mix:ImagingPerformanceAssessment>
                  <mix:ChangeHistory>
                     <mix:ImageProcessing>
                        <mix:SourceData>./PUL-BlueMountain/periodicals/bmtnaao/issues/1915/07_01/00000008.jp2</mix:SourceData>
                     </mix:ImageProcessing>
                  </mix:ChangeHistory>
               </mix:mix>
            </xmlData>
         </mdWrap>
      </techMD>
   </amdSec>
   <fileSec>
      <fileGrp ID="IMGGRP" USE="Images">
         <file ID="IMG00001" ADMID="techmd1" GROUPID="page1" CREATED="2015-08-19T14:00:34"
            MIMETYPE="image/jp2" SEQ="1" CHECKSUM="3e7c0f45f73bf626f34826ce1b292cd579939e48"
            CHECKSUMTYPE="SHA-1" SIZE="1072928">
            <FLocat LOCTYPE="URL"
               xlink:href="file:///usr/share/BlueMountain/astore/periodicals/bmtnaao/issues/1915/07_01/delivery/bmtnaao_1915-07_01_0001.jp2"
            />
         </file>
         <file ID="IMG00002" ADMID="techmd2" GROUPID="page2" CREATED="2015-08-19T14:00:40"
            MIMETYPE="image/jp2" SEQ="2" CHECKSUM="caa5e4a975916f71730ad164f619241e88f77c55"
            CHECKSUMTYPE="SHA-1" SIZE="1068873">
            <FLocat LOCTYPE="URL"
               xlink:href="file:///usr/share/BlueMountain/astore/periodicals/bmtnaao/issues/1915/07_01/delivery/bmtnaao_1915-07_01_0002.jp2"
            />
         </file>
         <file ID="IMG00003" ADMID="techmd3" GROUPID="page3" CREATED="2015-08-19T14:00:46"
            MIMETYPE="image/jp2" SEQ="3" CHECKSUM="7c70ed6086c95cc40ae669ae99c172f6f8c84d74"
            CHECKSUMTYPE="SHA-1" SIZE="1059395">
            <FLocat LOCTYPE="URL"
               xlink:href="file:///usr/share/BlueMountain/astore/periodicals/bmtnaao/issues/1915/07_01/delivery/bmtnaao_1915-07_01_0003.jp2"
            />
         </file>
         <file ID="IMG00004" ADMID="techmd4" GROUPID="page4" CREATED="2015-08-19T14:00:52"
            MIMETYPE="image/jp2" SEQ="4" CHECKSUM="8bfd7e661ec9e437e159d487f675997b1272f515"
            CHECKSUMTYPE="SHA-1" SIZE="1059294">
            <FLocat LOCTYPE="URL"
               xlink:href="file:///usr/share/BlueMountain/astore/periodicals/bmtnaao/issues/1915/07_01/delivery/bmtnaao_1915-07_01_0004.jp2"
            />
         </file>
         <file ID="IMG00005" ADMID="techmd5" GROUPID="page5" CREATED="2015-08-19T14:00:58"
            MIMETYPE="image/jp2" SEQ="5" CHECKSUM="848b2a210096d2b1842c78cc4f384d68fd76d3f2"
            CHECKSUMTYPE="SHA-1" SIZE="1059407">
            <FLocat LOCTYPE="URL"
               xlink:href="file:///usr/share/BlueMountain/astore/periodicals/bmtnaao/issues/1915/07_01/delivery/bmtnaao_1915-07_01_0005.jp2"
            />
         </file>
         <file ID="IMG00006" ADMID="techmd6" GROUPID="page6" CREATED="2015-08-19T14:01:04"
            MIMETYPE="image/jp2" SEQ="6" CHECKSUM="a52268face0f3a6279a9ddead05ed17aac67bf57"
            CHECKSUMTYPE="SHA-1" SIZE="1071093">
            <FLocat LOCTYPE="URL"
               xlink:href="file:///usr/share/BlueMountain/astore/periodicals/bmtnaao/issues/1915/07_01/delivery/bmtnaao_1915-07_01_0006.jp2"
            />
         </file>
      </fileGrp>
      <fileGrp ID="ALTOGRP" USE="OCR">
         <file ID="ALTO00001" GROUPID="page1" CREATED="2015-08-19T14:01:09" MIMETYPE="text/xml"
            CHECKSUM="8a1a78b03b62abcd8db172a4d1fb55e4f7d32b69" CHECKSUMTYPE="SHA-1" SIZE="5456">
            <FLocat LOCTYPE="URL" xlink:href="file://./alto/bmtnaao_1915-07_01_0001.alto.xml"/>
         </file>
         <file ID="ALTO00002" GROUPID="page2" CREATED="2015-08-19T14:01:09" MIMETYPE="text/xml"
            CHECKSUM="a6839980fd8027361caa8203ad79c6f236052a27" CHECKSUMTYPE="SHA-1" SIZE="6047">
            <FLocat LOCTYPE="URL" xlink:href="file://./alto/bmtnaao_1915-07_01_0002.alto.xml"/>
         </file>
         <file ID="ALTO00003" GROUPID="page3" CREATED="2015-08-19T14:01:09" MIMETYPE="text/xml"
            CHECKSUM="8fd75f7d69711d9a3acedab24976d453ab3b0750" CHECKSUMTYPE="SHA-1" SIZE="4187">
            <FLocat LOCTYPE="URL" xlink:href="file://./alto/bmtnaao_1915-07_01_0003.alto.xml"/>
         </file>
         <file ID="ALTO00004" GROUPID="page4" CREATED="2015-08-19T14:01:10" MIMETYPE="text/xml"
            CHECKSUM="f861dcc4ca5297a01a7b2607cc651d7400da072c" CHECKSUMTYPE="SHA-1" SIZE="6157">
            <FLocat LOCTYPE="URL" xlink:href="file://./alto/bmtnaao_1915-07_01_0004.alto.xml"/>
         </file>
         <file ID="ALTO00005" GROUPID="page5" CREATED="2015-08-19T14:01:10" MIMETYPE="text/xml"
            CHECKSUM="2739232c1f03d5e0bced72d9cd3db83701e3a570" CHECKSUMTYPE="SHA-1" SIZE="5385">
            <FLocat LOCTYPE="URL" xlink:href="file://./alto/bmtnaao_1915-07_01_0005.alto.xml"/>
         </file>
         <file ID="ALTO00006" GROUPID="page6" CREATED="2015-08-19T14:01:10" MIMETYPE="text/xml"
            CHECKSUM="dae3600bd16d1eac79a3bcdc0fec04ce016e1993" CHECKSUMTYPE="SHA-1" SIZE="417892">
            <FLocat LOCTYPE="URL" xlink:href="file://./alto/bmtnaao_1915-07_01_0006.alto.xml"/>
         </file>
      </fileGrp>
      <fileGrp ID="PDFGRP" USE="PDF">
         <file ID="PDF_ISSUELEVEL" CREATED="2015-08-19T14:01:21" MIMETYPE="application/pdf"
            CHECKSUM="1ea90f069019df37a031799725400b51df89df3b" CHECKSUMTYPE="SHA-1" SIZE="822566">
            <FLocat LOCTYPE="URL"
               xlink:href="file:///usr/share/BlueMountain/astore/periodicals/bmtnaao/issues/1915/07_01/bmtnaao_1915-07_01.pdf"
            />
         </file>
      </fileGrp>
   </fileSec>
   <structMap LABEL="Physical Structure" TYPE="PHYSICAL">
      <div ID="DIVP1" LABEL="" TYPE="Magazine" DMDID="dmd1">
         <div ID="DIVP2" ORDER="1" ORDERLABEL="1" TYPE="OUTSIDE_FRONT_COVER">
            <fptr>
               <par>
                  <area FILEID="IMG00001"/>
                  <area FILEID="ALTO00001" BETYPE="IDREF" BEGIN="P1"/>
               </par>
            </fptr>
         </div>
         <div ID="DIVP3" ORDER="2" ORDERLABEL="2" TYPE="INSIDE">
            <fptr>
               <par>
                  <area FILEID="IMG00002"/>
                  <area FILEID="ALTO00002" BETYPE="IDREF" BEGIN="P2"/>
               </par>
            </fptr>
         </div>
         <div ID="DIVP4" ORDER="3" ORDERLABEL="3" TYPE="INSIDE">
            <fptr>
               <par>
                  <area FILEID="IMG00003"/>
                  <area FILEID="ALTO00003" BETYPE="IDREF" BEGIN="P3"/>
               </par>
            </fptr>
         </div>
         <div ID="DIVP5" ORDER="4" ORDERLABEL="4" TYPE="INSIDE">
            <fptr>
               <par>
                  <area FILEID="IMG00004"/>
                  <area FILEID="ALTO00004" BETYPE="IDREF" BEGIN="P4"/>
               </par>
            </fptr>
         </div>
         <div ID="DIVP6" ORDER="5" ORDERLABEL="5" TYPE="INSIDE">
            <fptr>
               <par>
                  <area FILEID="IMG00005"/>
                  <area FILEID="ALTO00005" BETYPE="IDREF" BEGIN="P5"/>
               </par>
            </fptr>
         </div>
         <div ID="DIVP7" ORDER="6" ORDERLABEL="6" TYPE="INSIDE">
            <fptr>
               <par>
                  <area FILEID="IMG00006"/>
                  <area FILEID="ALTO00006" BETYPE="IDREF" BEGIN="P6"/>
               </par>
            </fptr>
         </div>
      </div>
   </structMap>
   <structMap LABEL="Logical Structure" TYPE="LOGICAL">
      <div ID="L.1" TYPE="Magazine" LABEL="291">
         <div ID="L.1.1" TYPE="Issue" LABEL="bmtnaao no. 5 07.1915">
            <div ID="L.1.1.1" TYPE="PublicationInfo" LABEL="Publication Information">
               <div ID="L.1.1.1.1" TYPE="GenericPubInfo" ORDER="1">
                  <fptr>
                     <area BETYPE="IDREF" FILEID="ALTO00001" BEGIN="P1_TB00002"/>
                  </fptr>
               </div>
               <div ID="L.1.1.1.2" TYPE="GenericPubInfo" ORDER="2">
                  <fptr>
                     <area BETYPE="IDREF" FILEID="ALTO00006" BEGIN="P6_TB00001"/>
                  </fptr>
               </div>
               <div ID="L.1.1.1.3" TYPE="GenericPubInfo" ORDER="3">
                  <fptr>
                     <area BETYPE="IDREF" FILEID="ALTO00006" BEGIN="P6_TB00002"/>
                  </fptr>
               </div>
               <div ID="L.1.1.1.4" TYPE="GenericPubInfo" ORDER="4">
                  <fptr>
                     <area BETYPE="IDREF" FILEID="ALTO00006" BEGIN="P6_TB00003"/>
                  </fptr>
               </div>
               <div ID="L.1.1.1.5" TYPE="GenericPubInfo" ORDER="5">
                  <fptr>
                     <area BETYPE="IDREF" FILEID="ALTO00006" BEGIN="P6_TB00010"/>
                  </fptr>
               </div>
            </div>
            <div ID="L.1.1.2" TYPE="EditorialContent" LABEL="Contents">
               <div ID="L.1.1.2.1" TYPE="Illustration" ORDER="1" DMDID="c001"
                  LABEL="ICI, C’EST ICI STIEGLITZ FOI ET AMOUR F. Picabia 1915 New York">
                  <div ID="L.1.1.2.1.1" TYPE="Image">
                     <fptr>
                        <area BETYPE="IDREF" FILEID="ALTO00001" BEGIN="P1_CB00001"/>
                     </fptr>
                  </div>
                  <div ID="L.1.1.2.1.2" TYPE="Caption">
                     <fptr>
                        <seq>
                           <area BETYPE="IDREF" FILEID="ALTO00001" BEGIN="P1_TB00001"/>
                           <area BETYPE="IDREF" FILEID="ALTO00001" BEGIN="P1_TB00003"/>
                           <area BETYPE="IDREF" FILEID="ALTO00001" BEGIN="P1_TB00004"/>
                        </seq>
                     </fptr>
                  </div>
               </div>
               <div ID="L.1.1.2.2" TYPE="Illustration" ORDER="1" DMDID="c002"
                  LABEL="F. Picabia Juillet 1915 New York LE SAINT DES SAINTS C’EST DE MOI QU’IL S’AGIT DANS CE PORTRAIT">
                  <div ID="L.1.1.2.2.1" TYPE="Image">
                     <fptr>
                        <area BETYPE="IDREF" FILEID="ALTO00002" BEGIN="P2_CB00001"/>
                     </fptr>
                  </div>
                  <div ID="L.1.1.2.2.2" TYPE="Caption">
                     <fptr>
                        <seq>
                           <area BETYPE="IDREF" FILEID="ALTO00002" BEGIN="P2_TB00001"/>
                           <area BETYPE="IDREF" FILEID="ALTO00002" BEGIN="P2_TB00002"/>
                           <area BETYPE="IDREF" FILEID="ALTO00002" BEGIN="P2_TB00003"/>
                        </seq>
                     </fptr>
                  </div>
               </div>
               <div ID="L.1.1.2.3" TYPE="Illustration" ORDER="1" DMDID="c003"
                  LABEL="VOILA HAVILAND T*. Picabia ■sis New York">
                  <div ID="L.1.1.2.3.1" TYPE="Image">
                     <fptr>
                        <area BETYPE="IDREF" FILEID="ALTO00003" BEGIN="P3_CB00001"/>
                     </fptr>
                  </div>
                  <div ID="L.1.1.2.3.2" TYPE="Caption">
                     <fptr>
                        <seq>
                           <area BETYPE="IDREF" FILEID="ALTO00003" BEGIN="P3_TB00001"/>
                           <area BETYPE="IDREF" FILEID="ALTO00003" BEGIN="P3_TB00002"/>
                           <area BETYPE="IDREF" FILEID="ALTO00003" BEGIN="P3_TB00003"/>
                        </seq>
                     </fptr>
                  </div>
               </div>
               <div ID="L.1.1.2.4" TYPE="Illustration" ORDER="1" DMDID="c004"
                  LABEL="F Picabia PORTRAIT D’UNE JEUNE FILLE AMERICAINE DANS L’ETAT DE NUDITÉ 5 Juillet 1915 New York">
                  <div ID="L.1.1.2.4.1" TYPE="Image">
                     <fptr>
                        <area BETYPE="IDREF" FILEID="ALTO00004" BEGIN="P4_CB00001"/>
                     </fptr>
                  </div>
                  <div ID="L.1.1.2.4.2" TYPE="Caption">
                     <fptr>
                        <seq>
                           <area BETYPE="IDREF" FILEID="ALTO00004" BEGIN="P4_TB00001"/>
                           <area BETYPE="IDREF" FILEID="ALTO00004" BEGIN="P4_TB00003"/>
                           <area BETYPE="IDREF" FILEID="ALTO00004" BEGIN="P4_TB00002"/>
                        </seq>
                     </fptr>
                  </div>
               </div>
               <div ID="L.1.1.2.5" TYPE="Illustration" ORDER="1" DMDID="c005"
                  LABEL="DE ZAYAS! DE ZAYAS! F. Picabia 1915 New York">
                  <div ID="L.1.1.2.5.1" TYPE="Image">
                     <fptr>
                        <area BETYPE="IDREF" FILEID="ALTO00005" BEGIN="P5_CB00001"/>
                     </fptr>
                  </div>
                  <div ID="L.1.1.2.5.2" TYPE="Caption">
                     <fptr>
                        <seq>
                           <area BETYPE="IDREF" FILEID="ALTO00005" BEGIN="P5_TB00001"/>
                           <area BETYPE="IDREF" FILEID="ALTO00005" BEGIN="P5_TB00002"/>
                           <area BETYPE="IDREF" FILEID="ALTO00005" BEGIN="P5_TB00003"/>
                        </seq>
                     </fptr>
                  </div>
               </div>
               <div ID="L.1.1.2.6" TYPE="TextContent" ORDER="6" DMDID="c006"
                  LABEL="New York n’a pas vu d’abord,—n’a pas voulu voir apres. Comme">
                  <div ID="L.1.1.2.6.1" TYPE="Byline">
                     <fptr>
                        <area BETYPE="IDREF" FILEID="ALTO00006" BEGIN="P6_TB00006"/>
                     </fptr>
                  </div>
                  <div ID="L.1.1.2.6.2" TYPE="Copy">
                     <div ID="L.1.1.2.6.2.1" TYPE="BodyContent">
                        <div ID="L.1.1.2.6.2.1.1" TYPE="Paragraph" ORDER="1">
                           <div ID="L.1.1.2.6.2.1.1.1" TYPE="Text">
                              <fptr>
                                 <seq>
                                    <area BETYPE="IDREF" FILEID="ALTO00006" BEGIN="P6_TB00004"/>
                                    <area BETYPE="IDREF" FILEID="ALTO00006" BEGIN="P6_TB00005"/>
                                 </seq>
                              </fptr>
                           </div>
                        </div>
                     </div>
                  </div>
               </div>
               <div ID="L.1.1.2.7" TYPE="TextContent" ORDER="7" DMDID="c007"
                  LABEL="New York, at first, did not see. Afterward she did not want to see. Like a circumspect">
                  <div ID="L.1.1.2.7.1" TYPE="Byline">
                     <fptr>
                        <area BETYPE="IDREF" FILEID="ALTO00006" BEGIN="P6_TB00009"/>
                     </fptr>
                  </div>
                  <div ID="L.1.1.2.7.2" TYPE="Copy">
                     <div ID="L.1.1.2.7.2.1" TYPE="BodyContent">
                        <div ID="L.1.1.2.7.2.1.1" TYPE="Paragraph" ORDER="1">
                           <div ID="L.1.1.2.7.2.1.1.1" TYPE="Text">
                              <fptr>
                                 <area BETYPE="IDREF" FILEID="ALTO00006" BEGIN="P6_TB00007"/>
                              </fptr>
                           </div>
                        </div>
                        <div ID="L.1.1.2.7.2.1.2" TYPE="Paragraph" ORDER="2">
                           <div ID="L.1.1.2.7.2.1.2.1" TYPE="Text">
                              <fptr>
                                 <area BETYPE="IDREF" FILEID="ALTO00006" BEGIN="P6_TB00008"/>
                              </fptr>
                           </div>
                        </div>
                     </div>
                  </div>
               </div>
            </div>
         </div>
      </div>
   </structMap>
</mets>
